crushfs/__init__.py
crushfs/async_client.py
crushfs/client.py
crushfs/enums.py
crushfs/error.py
crushfs/sync_client.py
crushfs-0.4.3.dist-info/LICENSE
crushfs-0.4.3.dist-info/METADATA
crushfs-0.4.3.dist-info/WHEEL
crushfs-0.4.3.dist-info/top_level.txt
crushfs-0.4.3.dist-info/RECORD
