Metadata-Version: 2.1
Name: crushfs
Version: 0.4.3
Summary: Python 3 client for CrushFS (sync and async)
Home-page: https://github.com/crushfs/crushfs-python-client
Author: David Poirier
Author-email: david@pxcrush.net
License: UNKNOWN
Keywords: crushfs
Platform: UNKNOWN
Classifier: Programming Language :: Python :: 3
Classifier: License :: OSI Approved :: Apache Software License
Classifier: Operating System :: OS Independent
Requires-Dist: aiohttp
Requires-Dist: requests
